README.md
setup.py
src/graph_inait/__init__.py
src/graph_inait.egg-info/PKG-INFO
src/graph_inait.egg-info/SOURCES.txt
src/graph_inait.egg-info/dependency_links.txt
src/graph_inait.egg-info/requires.txt
src/graph_inait.egg-info/top_level.txt