Metadata-Version: 2.1
Name: graph-inait
Version: 1.0.1
Summary: Python graph class.
Home-page: UNKNOWN
Author: Jose Mielgo
Author-email: mielgosez@gmail.com
License: UNKNOWN
Platform: UNKNOWN
Classifier: Programming Language :: Python :: 3
Classifier: License :: OSI Approved :: MIT License
Classifier: Operating System :: OS Independent
Requires-Python: >=3.6
